boto_session_manager/__init__.py
boto_session_manager/_version.py
boto_session_manager/clients.py
boto_session_manager/exc.py
boto_session_manager/manager.py
boto_session_manager/sentinel.py
boto_session_manager/services.py
boto_session_manager/docs/__init__.py
boto_session_manager/vendor/__init__.py
boto_session_manager/vendor/aws_sts.py
boto_session_manager-1.7.2.dist-info/AUTHORS.rst
boto_session_manager-1.7.2.dist-info/LICENSE.txt
boto_session_manager-1.7.2.dist-info/METADATA
boto_session_manager-1.7.2.dist-info/WHEEL
boto_session_manager-1.7.2.dist-info/top_level.txt
boto_session_manager-1.7.2.dist-info/RECORD
