Metadata-Version: 2.1
Name: boto-session-manager
Version: 1.7.2
Summary: Provides an alternative, or maybe a more user friendly way to use the native boto3 API.
Home-page: https://github.com/aws-samples/boto_session_manager-project
Download-URL: https://pypi.python.org/pypi/boto_session_manager/1.7.2#downloads
Author: Sanhe Hu
Author-email: husanhe@gmail.com
Maintainer: Sanhe Hu
Maintainer-email: husanhe@gmail.com
License: Apache License, Version 2.0
Platform: Windows
Platform: MacOS
Platform: Unix
Classifier: Development Status :: 5 - Production/Stable
Classifier: Intended Audience :: Developers
Classifier: License :: OSI Approved :: Apache Software License
Classifier: Natural Language :: English
Classifier: Operating System :: Microsoft :: Windows
Classifier: Operating System :: MacOS
Classifier: Operating System :: Unix
Classifier: Programming Language :: Python
Classifier: Programming Language :: Python :: 3 :: Only
Classifier: Programming Language :: Python :: 3.7
Classifier: Programming Language :: Python :: 3.8
Classifier: Programming Language :: Python :: 3.9
Classifier: Programming Language :: Python :: 3.10
Classifier: Programming Language :: Python :: 3.11
Classifier: Programming Language :: Python :: 3.12
Requires-Python: >=3.7
License-File: LICENSE.txt
License-File: AUTHORS.rst
Requires-Dist: boto3
Provides-Extra: docs
Requires-Dist: sphinx ==4.3.0 ; extra == 'docs'
Requires-Dist: sphinx-inline-tabs ==2021.8.17b10 ; extra == 'docs'
Requires-Dist: sphinx-jinja ==1.1.1 ; extra == 'docs'
Requires-Dist: sphinx-copybutton ==0.4.0 ; extra == 'docs'
Requires-Dist: rstobj ==0.0.7 ; extra == 'docs'
Requires-Dist: docfly ==1.0.2 ; extra == 'docs'
Requires-Dist: furo ==2021.8.31 ; extra == 'docs'
Provides-Extra: tests
Requires-Dist: boto3 ; extra == 'tests'
Requires-Dist: awscli ; extra == 'tests'
Requires-Dist: pytest ; extra == 'tests'
Requires-Dist: pytest-cov ; extra == 'tests'
